svg2tikz/.jukit/.jukit_info.json
svg2tikz/__init__.py
svg2tikz/tikz_export.py
svg2tikz/tikz_export_effect.inx
svg2tikz/tikz_export_output.inx
svg2tikz-3.3.4.dist-info/METADATA
svg2tikz-3.3.4.dist-info/WHEEL
svg2tikz-3.3.4.dist-info/entry_points.txt
svg2tikz-3.3.4.dist-info/licenses/LICENSE
svg2tikz-3.3.4.dist-info/RECORD
