Metadata-Version: 2.4
Name: svg2tikz
Version: 3.3.4
Summary: Tools for converting SVG graphics to TikZ/PGF code
License: GPL-2.0-or-later
License-File: LICENSE
Author: ldevillez
Author-email: louis.devillez@gmail.com
Maintainer: ldevillez
Maintainer-email: louis.devillez@gmail.com
Requires-Python: >=3.8,<4.0
Classifier: License :: OSI Approved :: GNU General Public License v2 or later (GPLv2+)
Classifier: Programming Language :: Python :: 3
Classifier: Programming Language :: Python :: 3.8
Classifier: Programming Language :: Python :: 3.9
Classifier: Programming Language :: Python :: 3.10
Classifier: Programming Language :: Python :: 3.11
Classifier: Programming Language :: Python :: 3.12
Classifier: Programming Language :: Python :: 3.13
Classifier: Programming Language :: Python :: 3.14
Requires-Dist: inkex (==1.4.0)
Requires-Dist: lxml (>=5.1.1,<6.0.0)
